setup.py
platrontools/__init__.py
platrontools/client.py
platrontools/utils.py
platrontools.egg-info/PKG-INFO
platrontools.egg-info/SOURCES.txt
platrontools.egg-info/dependency_links.txt
platrontools.egg-info/requires.txt
platrontools.egg-info/top_level.txt