Metadata-Version: 1.0
Name: platrontools
Version: 0.9
Summary: Python tools for Platron.ru
Home-page: https://bitbucket.org/05bit/py-platrontools
Author: Alexey Kinyov
Author-email: rudy@05bit.com
License: BSD
Keywords: platron,api
Platform: UNKNOWN
Classifier: Development Status :: 4 - Beta
Classifier: Operating System :: OS Independent
Classifier: License :: OSI Approved :: BSD License
Classifier: Intended Audience :: Developers
Classifier: Environment :: Web Environment
Classifier: Programming Language :: Python :: 2.5
Classifier: Programming Language :: Python :: 2.6
Classifier: Programming Language :: Python :: 2.7
